elasticsearch7_mcp_server/__init__.py
elasticsearch7_mcp_server/__main__.py
elasticsearch7_mcp_server/es_client.py
elasticsearch7_mcp_server/server.py
iflow_mcp_elasticsearch7_mcp_server-1.0.0.dist-info/METADATA
iflow_mcp_elasticsearch7_mcp_server-1.0.0.dist-info/WHEEL
iflow_mcp_elasticsearch7_mcp_server-1.0.0.dist-info/entry_points.txt
iflow_mcp_elasticsearch7_mcp_server-1.0.0.dist-info/licenses/LICENSE
iflow_mcp_elasticsearch7_mcp_server-1.0.0.dist-info/RECORD
