Metadata-Version: 2.4
Name: iflow-mcp_elasticsearch7-mcp-server
Version: 1.0.0
Summary: MCP Server for interacting with Elasticsearch 7.x
License:                                  Apache License
License-File: LICENSE
Requires-Python: >=3.10
Requires-Dist: elasticsearch<8.0.0,>=7.0.0
Requires-Dist: fastmcp>=0.4.0
Requires-Dist: mcp>=1.0.0
Requires-Dist: python-dotenv>=1.0.0
